ovos_plugin_vlc/__init__.py
ovos_plugin_vlc/version.py
ovos_plugin_vlc-0.0.2.dist-info/LICENSE
ovos_plugin_vlc-0.0.2.dist-info/METADATA
ovos_plugin_vlc-0.0.2.dist-info/WHEEL
ovos_plugin_vlc-0.0.2.dist-info/entry_points.txt
ovos_plugin_vlc-0.0.2.dist-info/top_level.txt
ovos_plugin_vlc-0.0.2.dist-info/RECORD
