Metadata-Version: 2.1
Name: ovos-plugin-vlc
Version: 0.0.2
Summary: vlc plugin for ovos
Home-page: https://github.com/OpenVoiceOS/ovos-vlc-plugin
Author: JarbasAi
Author-email: jarbasai@mailfence.com
License: Apache-2.0
Keywords: ovos audio plugin
Platform: UNKNOWN
Requires-Dist: ovos-plugin-manager>=0.0.26a29
Requires-Dist: python-vlc>=1.1.2
